{
	"multiple_panel": {
		"split_ratio": 0.6216006216006216,
		"split_panel0": {
			"split_ratio": 0.5,
			"split_panel0": {
				"split_ratio": 0.48749698857378854,
				"split_panel0": {
					"panelTypes": ["network", "viewer", "params"],
					"currentPanelIndex": 1,
					"panel_data": {
						"camera": "/cameras2/cameras2:sopGroup/perspectiveCamera1",
						"isViewerInitLayoutData": true,
						"linkIndex": 1,
						"overlayedNetwork": {
							"allowed": false,
							"displayed": false,
							"initLayoutData": {
								"camera": {
									"position": {
										"x": -200,
										"y": 125
									},
									"zoom": 1
								},
								"history": {
									"2": {
										"position": {
											"x": -550,
											"y": 100
										},
										"zoom": 1
									},
									"36": {
										"position": {
											"x": 350,
											"y": -1100
										},
										"zoom": 1
									},
									"47": {
										"position": {
											"x": 175,
											"y": -925
										},
										"zoom": 1
									},
									"84": {
										"position": {
											"x": 350,
											"y": -1100
										},
										"zoom": 1
									},
									"183": {
										"position": {
											"x": 0,
											"y": 0
										},
										"zoom": 1
									},
									"220": {
										"position": {
											"x": -150,
											"y": -150
										},
										"zoom": 1
									},
									"351": {
										"position": {
											"x": 0,
											"y": -100
										},
										"zoom": 1
									},
									"379": {
										"position": {
											"x": -275,
											"y": -725
										},
										"zoom": 1
									},
									"387": {
										"position": {
											"x": 300,
											"y": -125
										},
										"zoom": 1
									},
									"416": {
										"position": {
											"x": -275,
											"y": -725
										},
										"zoom": 1
									},
									"429": {
										"position": {
											"x": 0,
											"y": -100
										},
										"zoom": 1
									},
									"431": {
										"position": {
											"x": 325,
											"y": -275
										},
										"zoom": 1
									},
									"440": {
										"position": {
											"x": -100,
											"y": 100
										},
										"zoom": 1
									},
									"443": {
										"position": {
											"x": 0,
											"y": 0
										},
										"zoom": 1
									},
									"446": {
										"position": {
											"x": -25,
											"y": 0
										},
										"zoom": 1
									},
									"449": {
										"position": {
											"x": -325,
											"y": -450
										},
										"zoom": 1
									},
									"454": {
										"position": {
											"x": -100,
											"y": 100
										},
										"zoom": 1
									},
									"463": {
										"position": {
											"x": -100,
											"y": -550
										},
										"zoom": 1
									},
									"476": {
										"position": {
											"x": 0,
											"y": -25
										},
										"zoom": 1
									},
									"480": {
										"position": {
											"x": 0,
											"y": 0
										},
										"zoom": 1
									},
									"484": {
										"position": {
											"x": -150,
											"y": -50
										},
										"zoom": 1
									},
									"491": {
										"position": {
											"x": -200,
											"y": 125
										},
										"zoom": 1
									},
									"492": {
										"position": {
											"x": -325,
											"y": -450
										},
										"zoom": 1
									},
									"500": {
										"position": {
											"x": 325,
											"y": 150
										},
										"zoom": 1
									},
									"502": {
										"position": {
											"x": -200,
											"y": 125
										},
										"zoom": 1
									},
									"508": {
										"position": {
											"x": 300,
											"y": -125
										},
										"zoom": 1
									},
									"511": {
										"position": {
											"x": 600,
											"y": -775
										},
										"zoom": 1
									},
									"552": {
										"position": {
											"x": -50,
											"y": -600
										},
										"zoom": 1
									},
									"563": {
										"position": {
											"x": 275,
											"y": -275
										},
										"zoom": 1
									},
									"568": {
										"position": {
											"x": -325,
											"y": -450
										},
										"zoom": 1
									},
									"596": {
										"position": {
											"x": 0,
											"y": -200
										},
										"zoom": 1
									},
									"1793": {
										"position": {
											"x": -150,
											"y": 100
										},
										"zoom": 1
									},
									"1827": {
										"position": {
											"x": 0,
											"y": -500
										},
										"zoom": 1
									},
									"1830": {
										"position": {
											"x": -150,
											"y": 100
										},
										"zoom": 1
									},
									"1941": {
										"position": {
											"x": 0,
											"y": 0
										},
										"zoom": 1
									},
									"1955": {
										"position": {
											"x": 0,
											"y": 0
										},
										"zoom": 1
									},
									"2056": {
										"position": {
											"x": -150,
											"y": -50
										},
										"zoom": 1
									},
									"2493": {
										"position": {
											"x": -150,
											"y": -50
										},
										"zoom": 1
									},
									"2779": {
										"position": {
											"x": 100,
											"y": 50
										},
										"zoom": 1
									},
									"2838": {
										"position": {
											"x": -200,
											"y": 200
										},
										"zoom": 1
									},
									"2963": {
										"position": {
											"x": 150,
											"y": -350
										},
										"zoom": 1
									},
									"3098": {
										"position": {
											"x": 150,
											"y": -350
										},
										"zoom": 1
									},
									"3164": {
										"position": {
											"x": -150,
											"y": -50
										},
										"zoom": 1
									},
									"3263": {
										"position": {
											"x": 150,
											"y": -350
										},
										"zoom": 1
									},
									"3411": {
										"position": {
											"x": -150,
											"y": -50
										},
										"zoom": 1
									},
									"7948": {
										"position": {
											"x": 125,
											"y": -400
										},
										"zoom": 1
									}
								},
								"paramsDisplayed": false,
								"linkIndex": 1
							}
						}
					}
				},
				"split_panel1": {
					"panelTypes": ["network", "viewer", "params"],
					"currentPanelIndex": 2,
					"panel_data": {
						"active_folder": 555,
						"linkIndex": 1
					}
				},
				"split_mode": "horizontal"
			},
			"split_panel1": {
				"panelTypes": ["network", "viewer", "params", "spreadsheet", "sceneTree"],
				"currentPanelIndex": 4,
				"panel_data": {
					"mask": "*"
				}
			},
			"split_mode": "vertical"
		},
		"split_panel1": {
			"panelTypes": ["network", "params", "performance"],
			"currentPanelIndex": 0,
			"panel_data": {
				"camera": {
					"position": {
						"x": -133.31290915419333,
						"y": 13.176621207493554
					},
					"zoom": 0.8593635948046915
				},
				"history": {
					"2": {
						"position": {
							"x": 67.38070440117923,
							"y": 152.6836900409188
						},
						"zoom": 1.181017341124402
					},
					"36": {
						"position": {
							"x": 222.5545309645089,
							"y": -989.7979430520302
						},
						"zoom": 0.6276211921800005
					},
					"47": {
						"position": {
							"x": -239.41089927238133,
							"y": -1158.7268429386136
						},
						"zoom": 0.6276211921800007
					},
					"84": {
						"position": {
							"x": 203.10893555520462,
							"y": -1041.269381289289
						},
						"zoom": 0.6276211921800005
					},
					"183": {
						"position": {
							"x": -201.40673113985247,
							"y": -94.91351817055717
						},
						"zoom": 0.8596162615637897
					},
					"220": {
						"position": {
							"x": -342.5430509387567,
							"y": -118.8396541274611
						},
						"zoom": 0.7366991397945483
					},
					"351": {
						"position": {
							"x": 0,
							"y": -100
						},
						"zoom": 1.1809800000000008
					},
					"379": {
						"position": {
							"x": -597.9362169786887,
							"y": -737.3359594398336
						},
						"zoom": 0.5648590729620003
					},
					"387": {
						"position": {
							"x": 300,
							"y": -102.84321417793794
						},
						"zoom": 1.0628820000000008
					},
					"416": {
						"position": {
							"x": -579.2040659023884,
							"y": -589.848992103321
						},
						"zoom": 0.4111546429971196
					},
					"429": {
						"position": {
							"x": 0,
							"y": -100
						},
						"zoom": 0.9565938000000016
					},
					"431": {
						"position": {
							"x": 271.7191487950406,
							"y": -4.071834856926682
						},
						"zoom": 1.0628820000000008
					},
					"440": {
						"position": {
							"x": 127.24877590674538,
							"y": 355.5625454733766
						},
						"zoom": 0.9565938000000026
					},
					"443": {
						"position": {
							"x": 0,
							"y": 0
						},
						"zoom": 0.6276211921800003
					},
					"446": {
						"position": {
							"x": -25,
							"y": 0
						},
						"zoom": 0.6276211921800003
					},
					"449": {
						"position": {
							"x": 46.301721603009355,
							"y": -323.6421409038743
						},
						"zoom": 0.9810698726468243
					},
					"454": {
						"position": {
							"x": -189.43266856193316,
							"y": 436.4163073609273
						},
						"zoom": 1.0628820000000043
					},
					"463": {
						"position": {
							"x": 441.55093653677,
							"y": -693.9104800717132
						},
						"zoom": 0.6923106795301471
					},
					"476": {
						"position": {
							"x": 0,
							"y": -25
						},
						"zoom": 0.6276211921800003
					},
					"480": {
						"position": {
							"x": -114.9299384826288,
							"y": -26.118364061567547
						},
						"zoom": 1.3122000000000014
					},
					"484": {
						"position": {
							"x": -150,
							"y": -50
						},
						"zoom": 0.6286211921800003
					},
					"491": {
						"position": {
							"x": -133.31290915419333,
							"y": 13.176621207493554
						},
						"zoom": 0.8593635948046915
					},
					"492": {
						"position": {
							"x": -207.34465661328625,
							"y": -504.7145088881679
						},
						"zoom": 0.8831974532833746
					},
					"500": {
						"position": {
							"x": 1656.89270903425,
							"y": 490.5155378572821
						},
						"zoom": 0.6266935707372525
					},
					"502": {
						"position": {
							"x": 311.85510438868266,
							"y": -1.3992487130944085
						},
						"zoom": 0.6973568802000008
					},
					"508": {
						"position": {
							"x": 300,
							"y": -125
						},
						"zoom": 0.6276211921800003
					},
					"511": {
						"position": {
							"x": 1771.2041469861015,
							"y": 460.74501422377415
						},
						"zoom": 0.9565938000000012
					},
					"552": {
						"position": {
							"x": -127.58165161570884,
							"y": -724.5853058473938
						},
						"zoom": 1.0628820000000017
					},
					"563": {
						"position": {
							"x": 14.8177700461986,
							"y": -538.561396421157
						},
						"zoom": 0.7748409780000022
					},
					"568": {
						"position": {
							"x": -121.24781326552068,
							"y": -213.79283291569268
						},
						"zoom": 0.882962885382142
					},
					"596": {
						"position": {
							"x": 0,
							"y": -200
						},
						"zoom": 0.6276211921800003
					},
					"1793": {
						"position": {
							"x": -20.068525352337765,
							"y": -72.72022453181373
						},
						"zoom": 1.1228458158734158
					},
					"1827": {
						"position": {
							"x": 0,
							"y": -500
						},
						"zoom": 0.7366991397945483
					},
					"1830": {
						"position": {
							"x": 70.87104058591447,
							"y": -20.867849611635094
						},
						"zoom": 1.122845815873416
					},
					"1941": {
						"position": {
							"x": -284.1816852179578,
							"y": -318.4271544632819
						},
						"zoom": 0.6266602546800025
					},
					"1955": {
						"position": {
							"x": -17.422929844064075,
							"y": 0
						},
						"zoom": 0.8609344200000003
					},
					"2056": {
						"position": {
							"x": -166.90633987216884,
							"y": -141.13104381282596
						},
						"zoom": 0.6962891718666699
					},
					"2493": {
						"position": {
							"x": 29.340638052791633,
							"y": 6.736537171984779
						},
						"zoom": 0.8609344200000006
					},
					"2779": {
						"position": {
							"x": -43.00740816007789,
							"y": 7.6622804789243215
						},
						"zoom": 1.0628820000000008
					},
					"2838": {
						"position": {
							"x": -200,
							"y": 200
						},
						"zoom": 0.6276211921800026
					},
					"2963": {
						"position": {
							"x": 62.34496318961517,
							"y": -483.214094820226
						},
						"zoom": 0.6973568802000015
					},
					"3098": {
						"position": {
							"x": 131.2275969093895,
							"y": -350
						},
						"zoom": 0.6964841995359382
					},
					"3164": {
						"position": {
							"x": -167.9811188251122,
							"y": -2.056396671452376
						},
						"zoom": 0.5648590729620013
					},
					"3263": {
						"position": {
							"x": -10.964983998303182,
							"y": -181.6373287177907
						},
						"zoom": 0.7748409780000026
					},
					"3411": {
						"position": {
							"x": -175.14028876243137,
							"y": -190.06731114433276
						},
						"zoom": 1.0637546806640643
					},
					"7948": {
						"position": {
							"x": 125,
							"y": -400
						},
						"zoom": 0.6276211921800026
					}
				},
				"paramsDisplayed": false,
				"linkIndex": 1
			}
		},
		"split_mode": "horizontal"
	},
	"currentNodes": ["/particles1/particlesSystemGpu1", "/", "/", "/", "/", "/", "/", "/"],
	"navigationHistory": {
		"nodePaths": {
			"1": [
				"/particles1",
				"/particles1/particlesSystemGpu1",
				"/particles1",
				"/particles1/particlesSystemGpu1",
				"/particles1",
				"/",
				"/particles1",
				"/particles1/particlesSystemGpu1",
				"/particles1",
				"/",
				"/particles1",
				"/particles1/particlesSystemGpu1",
				"/particles1",
				"/particles1/MAT",
				"/particles1/MAT/meshBasicBuilder_INSTANCES_PARTICLES",
				"/particles1/MAT",
				"/particles1",
				"/particles1/particlesSystemGpu1",
				"/particles1",
				"/particles1/particlesSystemGpu1"
			],
			"2": ["/", "/", "/", "/", "/", "/", "/", "/", "/", "/", "/", "/", "/", "/", "/", "/"],
			"3": ["/", "/", "/", "/", "/", "/", "/", "/", "/", "/", "/", "/", "/", "/", "/", "/"],
			"4": ["/", "/", "/", "/", "/", "/", "/", "/", "/", "/", "/", "/", "/", "/", "/", "/"],
			"5": ["/", "/", "/", "/", "/", "/", "/", "/", "/", "/", "/", "/", "/", "/", "/", "/"],
			"6": ["/", "/", "/", "/", "/", "/", "/", "/", "/", "/", "/", "/", "/", "/", "/", "/"],
			"7": ["/", "/", "/", "/", "/", "/", "/", "/", "/", "/", "/", "/", "/", "/", "/", "/"],
			"8": ["/", "/", "/", "/", "/", "/", "/", "/", "/", "/", "/", "/", "/", "/", "/", "/"]
		},
		"index": {
			"1": 19,
			"2": 0,
			"3": 0,
			"4": 0,
			"5": 0,
			"6": 0,
			"7": 0,
			"8": 0
		}
	},
	"fullscreenPanelId": null,
	"saveOptions": {
		"createExport": false,
		"checkRemoteAssetsUse": true,
		"minimizeFilesCount": false,
		"compressJs": true,
		"createZip": false,
		"runPostExportCommand": false
	},
	"paramsModal": []
}
